COMPATIBILITY.html
COMPATIBILITY.md
COPYING.txt
DEVELOPMENT.html
DEVELOPMENT.md
MANIFEST.in
QUICK-START.html
QUICK-START.md
README.html
README.md
TODO.html
TODO.md
awlsim-client
awlsim-covreport
awlsim-gui
awlsim-linuxcnc-hal
awlsim-proupgrade
awlsim-server
awlsim-server.service
awlsim-symtab
awlsim-test
awlsim-win.cmd
awlsimhw_pyprofibus.conf
setup.py
awlsim/__init__.py
awlsim.egg-info/PKG-INFO
awlsim.egg-info/SOURCES.txt
awlsim.egg-info/dependency_links.txt
awlsim.egg-info/top_level.txt
awlsim/awlcompiler/__init__.py
awlsim/awlcompiler/insntrans.py
awlsim/awlcompiler/optrans.py
awlsim/awlcompiler/tokenizer.py
awlsim/awlcompiler/translator.py
awlsim/awloptimizer/__init__.py
awlsim/awloptimizer/awloptimizer.py
awlsim/awloptimizer/base.py
awlsim/awloptimizer/opt_biefwd.py
awlsim/awloptimizer/opt_lblrem.py
awlsim/awloptimizer/opt_noprem.py
awlsim/common/__init__.py
awlsim/common/blocker.py
awlsim/common/blockinfo.py
awlsim/common/codevalidator.py
awlsim/common/compat.py
awlsim/common/cpuconfig.py
awlsim/common/cpuspecs.pxd.in
awlsim/common/cpuspecs.py
awlsim/common/cython_support.pxd.in
awlsim/common/cython_support.pyx.in
awlsim/common/datatypehelpers.pxd.in
awlsim/common/datatypehelpers.py
awlsim/common/debug.py
awlsim/common/dynamic_import.py
awlsim/common/enumeration.py
awlsim/common/env.py
awlsim/common/exceptions.py
awlsim/common/hwmod.py
awlsim/common/immutable.py
awlsim/common/lpfilter.pxd.in
awlsim/common/lpfilter.py
awlsim/common/mlock.py
awlsim/common/monotonic.pxd.in
awlsim/common/monotonic.py
awlsim/common/movingavg.pxd.in
awlsim/common/movingavg.py
awlsim/common/namevalidation.py
awlsim/common/net.py
awlsim/common/profiler.py
awlsim/common/project.py
awlsim/common/project_legacy.py
awlsim/common/refmanager.py
awlsim/common/sources.py
awlsim/common/subprocess_wrapper.py
awlsim/common/templates.py
awlsim/common/util.py
awlsim/common/version.py
awlsim/common/wordpacker.py
awlsim/common/xmlfactory.py
awlsim/core/__init__.py
awlsim/core/blockinterface.py
awlsim/core/blocks.pxd.in
awlsim/core/blocks.py
awlsim/core/callstack.pxd.in
awlsim/core/callstack.py
