Metadata-Version: 2.1
Name: awlsim
Version: 0.77.1
Summary: S7 compatible Programmable Logic Controller PLC/SPS (AWL, STL, FUP, FBD)
Home-page: https://bues.ch/a/awlsim
Author: Michael Buesch
Author-email: m@bues.ch
License: GNU General Public License v2 or later
Keywords: AWL STL FUP FBD SPS PLC emulator simulator Step-7 Siemens PROFIBUS LinuxCNC PiXtend RaspberryPi
Classifier: Development Status :: 4 - Beta
Classifier: Environment :: Console
Classifier: Environment :: Win32 (MS Windows)
Classifier: Environment :: X11 Applications
Classifier: Intended Audience :: Developers
Classifier: Intended Audience :: Education
Classifier: Intended Audience :: Information Technology
Classifier: Intended Audience :: Manufacturing
Classifier: Intended Audience :: Science/Research
Classifier: License :: OSI Approved :: GNU General Public License v2 or later (GPLv2+)
Classifier: Operating System :: Microsoft :: Windows
Classifier: Operating System :: POSIX
Classifier: Operating System :: POSIX :: Linux
Classifier: Programming Language :: Cython
Classifier: Programming Language :: Python
Classifier: Programming Language :: Python :: 2.7
Classifier: Programming Language :: Python :: 3
Classifier: Programming Language :: Python :: Implementation :: CPython
Classifier: Programming Language :: Python :: Implementation :: PyPy
Classifier: Topic :: Education
Classifier: Topic :: Home Automation
Classifier: Topic :: Scientific/Engineering
Classifier: Topic :: Software Development
Classifier: Topic :: Software Development :: Interpreters
Classifier: Topic :: Software Development :: Embedded Systems
Classifier: Topic :: Software Development :: Testing
Classifier: Topic :: System :: Emulators
Requires-Python: >=2.7, !=3.0.*, !=3.1.*, !=3.2.*
License-File: COPYING.txt
